pyramid_htmldoom/__init__.py
pyramid_htmldoom-0.3.dist-info/LICENSE
pyramid_htmldoom-0.3.dist-info/METADATA
pyramid_htmldoom-0.3.dist-info/WHEEL
pyramid_htmldoom-0.3.dist-info/top_level.txt
pyramid_htmldoom-0.3.dist-info/RECORD
